notebookutils/__init__.py
notebookutils/credentials.py
notebookutils/data.py
notebookutils/fs.py
notebookutils/lakehouse.py
notebookutils/notebook.py
notebookutils/runtime.py
notebookutils/session.py
notebookutils/udf.py
notebookutils/variableLibrary.py
notebookutils/warehouse.py
notebookutils/workspace.py
notebookutils/mssparkutils/__init__.py
notebookutils/mssparkutils/credentials.py
notebookutils/mssparkutils/env.py
notebookutils/mssparkutils/fs.py
notebookutils/mssparkutils/lakehouse.py
notebookutils/mssparkutils/notebook.py
notebookutils/mssparkutils/runtime.py
notebookutils/mssparkutils/session.py
dummy_notebookutils_reborn-1.1.11.dist-info/METADATA
dummy_notebookutils_reborn-1.1.11.dist-info/WHEEL
dummy_notebookutils_reborn-1.1.11.dist-info/licenses/LICENSE
dummy_notebookutils_reborn-1.1.11.dist-info/RECORD
