Metadata-Version: 2.4
Name: dummy-notebookutils-reborn
Version: 1.1.11
Summary: A package that allows to use synapse mssparkutils without actual functionality. This helps to generate the build. Unofficial fork of dummy-notebookutils.
Project-URL: Homepage, https://github.com/wtfzambo/notebookutils
Project-URL: Issues, https://github.com/wtfzambo/notebookutils/issues
License-Expression: MIT
License-File: LICENSE
Classifier: Programming Language :: Python :: 3
Requires-Python: >=3.10
